ffmpegp/__init__.py
ffmpegp/__main__.py
ffmpegp-1.30.dist-info/licenses/LICENSE
ffmpegp-1.30.dist-info/METADATA
ffmpegp-1.30.dist-info/WHEEL
ffmpegp-1.30.dist-info/entry_points.txt
ffmpegp-1.30.dist-info/top_level.txt
ffmpegp-1.30.dist-info/RECORD
