Metadata-Version: 2.4
Name: ffmpegp
Version: 1.30
Summary: ffmpegp is an enhanced version of FFmpeg, offering additional features and functionalities to extend its powerful media processing capabilities.
Author: Ankush Bhagat
Author-email: <ankushbhagatofficial@gmail.com>
Keywords: python,ffmpeg,ffmpegp,automation,converter,encoding,progressbar
Classifier: Intended Audience :: Developers
Classifier: Programming Language :: Python :: 3
Classifier: Operating System :: Unix
Classifier: Operating System :: MacOS :: MacOS X
Classifier: Operating System :: Microsoft :: Windows
License-File: LICENSE
Requires-Dist: jsonpath_ng
Requires-Dist: pyargument
Dynamic: author
Dynamic: author-email
Dynamic: classifier
Dynamic: description
Dynamic: description-content-type
Dynamic: keywords
Dynamic: license-file
Dynamic: requires-dist
Dynamic: summary
